{
  "pipelineId" : "IngestingLocalDataintoAzureDataLakeStorec8d1d823-9fb7-4c13-bd55-1d77f1526f06",
  "rev" : "0",
  "user" : "admin",
  "status" : "STOPPED",
  "message" : "The pipeline was stopped. The last committed source offset is {$com.streamsets.pipeline.stage.origin.spooldir.SpoolDirSource.offset.version$=1, nyc_taxi_data.csv={\"POS\":\"-1\"}}.",
  "timeStamp" : 1525945116832,
  "attributes" : {
    "IS_REMOTE_PIPELINE" : false,
    "RUNTIME_PARAMETERS" : null
  },
  "executionMode" : "STANDALONE",
  "metrics" : "{\n  \"version\" : \"3.0.0\",\n  \"gauges\" : {\n    \"RuntimeStatsGauge.gauge\" : {\n      \"value\" : {\n        \"batchCount\" : 7,\n        \"timeOfLastReceivedRecord\" : 1525945049963,\n        \"lastBatchInputRecordsCount\" : 0,\n        \"lastBatchOutputRecordsCount\" : 0,\n        \"lastBatchErrorRecordsCount\" : 0,\n        \"lastBatchErrorMessagesCount\" : 0,\n        \"totalRunners\" : 1,\n        \"availableRunners\" : 1\n      }\n    },\n    \"custom.Directory_01.Spool Directory Metrics for Thread - 0.gauge\" : {\n      \"value\" : {\n        \"Status\" : \"BATCH_GENERATED\",\n        \"Current Offset\" : \"-1\",\n        \"Thread Name\" : \"Spool Directory Runner - 0\",\n        \"Current File\" : \"\"\n      }\n    },\n    \"health.DataObserverRunnable.gauge\" : {\n      \"value\" : {\n        \"threadName\" : \"DataObserverRunnable\",\n        \"scheduledDelay\" : -1,\n        \"timestamp\" : 1525945116158\n      }\n    },\n    \"health.MetricObserverRunnable.gauge\" : {\n      \"value\" : {\n        \"threadName\" : \"MetricObserverRunnable\",\n        \"scheduledDelay\" : 1,\n        \"timestamp\" : 1525945115017\n      }\n    },\n    \"health.MetricsEventRunnable.gauge\" : {\n      \"value\" : {\n        \"threadName\" : \"MetricsEventRunnable\",\n        \"scheduledDelay\" : 2000,\n        \"timestamp\" : 1525945115963\n      }\n    },\n    \"health.ProductionPipelineRunnable.gauge\" : {\n      \"value\" : null\n    },\n    \"health.RulesConfigLoaderRunnable.gauge\" : {\n      \"value\" : {\n        \"threadName\" : \"RulesConfigLoaderRunnable\",\n        \"scheduledDelay\" : 2,\n        \"timestamp\" : 1525945115017\n      }\n    },\n    \"jvm.buffers.direct.capacity\" : {\n      \"value\" : 1534190\n    },\n    \"jvm.buffers.direct.count\" : {\n      \"value\" : 54\n    },\n    \"jvm.buffers.direct.used\" : {\n      \"value\" : 1534190\n    },\n    \"jvm.buffers.mapped.capacity\" : {\n      \"value\" : 0\n    },\n    \"jvm.buffers.mapped.count\" : {\n      \"value\" : 0\n    },\n    \"jvm.buffers.mapped.used\" : {\n      \"value\" : 0\n    },\n    \"jvm.files\" : {\n      \"value\" : 0.012848096437018387\n    },\n    \"jvm.garbage.ConcurrentMarkSweep.count\" : {\n      \"value\" : 3\n    },\n    \"jvm.garbage.ConcurrentMarkSweep.time\" : {\n      \"value\" : 391\n    },\n    \"jvm.garbage.ParNew.count\" : {\n      \"value\" : 126\n    },\n    \"jvm.garbage.ParNew.time\" : {\n      \"value\" : 14930\n    },\n    \"jvm.memory.heap.committed\" : {\n      \"value\" : 1056309248\n    },\n    \"jvm.memory.heap.init\" : {\n      \"value\" : 1073741824\n    },\n    \"jvm.memory.heap.max\" : {\n      \"value\" : 1056309248\n    },\n    \"jvm.memory.heap.usage\" : {\n      \"value\" : 0.43701258970706275\n    },\n    \"jvm.memory.heap.used\" : {\n      \"value\" : 461620440\n    },\n    \"jvm.memory.non-heap.committed\" : {\n      \"value\" : 168869888\n    },\n    \"jvm.memory.non-heap.init\" : {\n      \"value\" : 2555904\n    },\n    \"jvm.memory.non-heap.max\" : {\n      \"value\" : -1\n    },\n    \"jvm.memory.non-heap.usage\" : {\n      \"value\" : -1.5161188E8\n    },\n    \"jvm.memory.non-heap.used\" : {\n      \"value\" : 151611880\n    },\n    \"jvm.memory.pools.CMS-Old-Gen.committed\" : {\n      \"value\" : 899284992\n    },\n    \"jvm.memory.pools.CMS-Old-Gen.init\" : {\n      \"value\" : 899284992\n    },\n    \"jvm.memory.pools.CMS-Old-Gen.max\" : {\n      \"value\" : 899284992\n    },\n    \"jvm.memory.pools.CMS-Old-Gen.usage\" : {\n      \"value\" : 0.36766306892843154\n    },\n    \"jvm.memory.pools.CMS-Old-Gen.used\" : {\n      \"value\" : 330633880\n    },\n    \"jvm.memory.pools.Code-Cache.committed\" : {\n      \"value\" : 47185920\n    },\n    \"jvm.memory.pools.Code-Cache.init\" : {\n      \"value\" : 2555904\n    },\n    \"jvm.memory.pools.Code-Cache.max\" : {\n      \"value\" : 251658240\n    },\n    \"jvm.memory.pools.Code-Cache.usage\" : {\n      \"value\" : 0.18602015177408854\n    },\n    \"jvm.memory.pools.Code-Cache.used\" : {\n      \"value\" : 46813504\n    },\n    \"jvm.memory.pools.Compressed-Class-Space.committed\" : {\n      \"value\" : 15564800\n    },\n    \"jvm.memory.pools.Compressed-Class-Space.init\" : {\n      \"value\" : 0\n    },\n    \"jvm.memory.pools.Compressed-Class-Space.max\" : {\n      \"value\" : 1073741824\n    },\n    \"jvm.memory.pools.Compressed-Class-Space.usage\" : {\n      \"value\" : 0.012710273265838623\n    },\n    \"jvm.memory.pools.Compressed-Class-Space.used\" : {\n      \"value\" : 13647552\n    },\n    \"jvm.memory.pools.Metaspace.committed\" : {\n      \"value\" : 106119168\n    },\n    \"jvm.memory.pools.Metaspace.init\" : {\n      \"value\" : 0\n    },\n    \"jvm.memory.pools.Metaspace.max\" : {\n      \"value\" : -1\n    },\n    \"jvm.memory.pools.Metaspace.usage\" : {\n      \"value\" : 0.8590587517610391\n    },\n    \"jvm.memory.pools.Metaspace.used\" : {\n      \"value\" : 91162600\n    },\n    \"jvm.memory.pools.Par-Eden-Space.committed\" : {\n      \"value\" : 139591680\n    },\n    \"jvm.memory.pools.Par-Eden-Space.init\" : {\n      \"value\" : 139591680\n    },\n    \"jvm.memory.pools.Par-Eden-Space.max\" : {\n      \"value\" : 139591680\n    },\n    \"jvm.memory.pools.Par-Eden-Space.usage\" : {\n      \"value\" : 0.8386240784551057\n    },\n    \"jvm.memory.pools.Par-Eden-Space.used\" : {\n      \"value\" : 117064944\n    },\n    \"jvm.memory.pools.Par-Survivor-Space.committed\" : {\n      \"value\" : 17432576\n    },\n    \"jvm.memory.pools.Par-Survivor-Space.init\" : {\n      \"value\" : 17432576\n    },\n    \"jvm.memory.pools.Par-Survivor-Space.max\" : {\n      \"value\" : 17432576\n    },\n    \"jvm.memory.pools.Par-Survivor-Space.usage\" : {\n      \"value\" : 0.7985977517034775\n    },\n    \"jvm.memory.pools.Par-Survivor-Space.used\" : {\n      \"value\" : 13921616\n    },\n    \"jvm.memory.total.committed\" : {\n      \"value\" : 1225179136\n    },\n    \"jvm.memory.total.init\" : {\n      \"value\" : 1076297728\n    },\n    \"jvm.memory.total.max\" : {\n      \"value\" : 1056309247\n    },\n    \"jvm.memory.total.used\" : {\n      \"value\" : 613233600\n    },\n    \"jvm.threads.blocked.count\" : {\n      \"value\" : 1\n    },\n    \"jvm.threads.count\" : {\n      \"value\" : 79\n    },\n    \"jvm.threads.daemon.count\" : {\n      \"value\" : 75\n    },\n    \"jvm.threads.deadlock.count\" : {\n      \"value\" : 0\n    },\n    \"jvm.threads.deadlocks\" : {\n      \"value\" : [ ]\n    },\n    \"jvm.threads.new.count\" : {\n      \"value\" : 0\n    },\n    \"jvm.threads.runnable.count\" : {\n      \"value\" : 4\n    },\n    \"jvm.threads.terminated.count\" : {\n      \"value\" : 0\n    },\n    \"jvm.threads.timed_waiting.count\" : {\n      \"value\" : 15\n    },\n    \"jvm.threads.waiting.count\" : {\n      \"value\" : 59\n    },\n    \"runner.0.gauge\" : {\n      \"value\" : {\n        \"currentStage\" : \"IDLE\",\n        \"stageStartTime\" : 1525945116794,\n        \"offsetValue\" : \"\",\n        \"batchCount\" : 8,\n        \"offsetKey\" : \"\",\n        \"batchStartTime\" : 0\n      }\n    }\n  },\n  \"counters\" : {\n    \"custom.Directory_01.pending.files.counter\" : {\n      \"count\" : 0\n    },\n    \"pipeline.batchCount.counter\" : {\n      \"count\" : 7\n    },\n    \"pipeline.batchErrorMessages.counter\" : {\n      \"count\" : 0\n    },\n    \"pipeline.batchErrorRecords.counter\" : {\n      \"count\" : 0\n    },\n    \"pipeline.batchInputRecords.counter\" : {\n      \"count\" : 5386\n    },\n    \"pipeline.batchOutputRecords.counter\" : {\n      \"count\" : 5386\n    },\n    \"pipeline.memoryConsumed.counter\" : {\n      \"count\" : 0\n    },\n    \"stage.Directory_01.errorRecords.counter\" : {\n      \"count\" : 0\n    },\n    \"stage.Directory_01.inputRecords.counter\" : {\n      \"count\" : 0\n    },\n    \"stage.Directory_01.memoryConsumed.counter\" : {\n      \"count\" : 0\n    },\n    \"stage.Directory_01.outputRecords.counter\" : {\n      \"count\" : 5386\n    },\n    \"stage.Directory_01.stageErrors.counter\" : {\n      \"count\" : 0\n    },\n    \"stage.Directory_01:Directory_01OutputLane15260465352240.outputRecords.counter\" : {\n      \"count\" : 5386\n    },\n    \"stage.Elasticsearch_01.errorRecords.counter\" : {\n      \"count\" : 0\n    },\n    \"stage.Elasticsearch_01.inputRecords.counter\" : {\n      \"count\" : 5386\n    },\n    \"stage.Elasticsearch_01.memoryConsumed.counter\" : {\n      \"count\" : 0\n    },\n    \"stage.Elasticsearch_01.outputRecords.counter\" : {\n      \"count\" : 5386\n    },\n    \"stage.Elasticsearch_01.stageErrors.counter\" : {\n      \"count\" : 0\n    },\n    \"stage.FieldMasker_01.errorRecords.counter\" : {\n      \"count\" : 0\n    },\n    \"stage.FieldMasker_01.inputRecords.counter\" : {\n      \"count\" : 5386\n    },\n    \"stage.FieldMasker_01.memoryConsumed.counter\" : {\n      \"count\" : 0\n    },\n    \"stage.FieldMasker_01.outputRecords.counter\" : {\n      \"count\" : 5386\n    },\n    \"stage.FieldMasker_01.stageErrors.counter\" : {\n      \"count\" : 0\n    },\n    \"stage.FieldMasker_01:FieldMasker_01OutputLane15260466335330.outputRecords.counter\" : {\n      \"count\" : 5386\n    }\n  },\n  \"histograms\" : {\n    \"pipeline.errorRecordsPerBatch.histogramM5\" : {\n      \"count\" : 7,\n      \"max\" : 0,\n      \"mean\" : 0.0,\n      \"min\" : 0,\n      \"p50\" : 0.0,\n      \"p75\" : 0.0,\n      \"p95\" : 0.0,\n      \"p98\" : 0.0,\n      \"p99\" : 0.0,\n      \"p999\" : 0.0,\n      \"stddev\" : 0.0\n    },\n    \"pipeline.errorsPerBatch.histogramM5\" : {\n      \"count\" : 7,\n      \"max\" : 0,\n      \"mean\" : 0.0,\n      \"min\" : 0,\n      \"p50\" : 0.0,\n      \"p75\" : 0.0,\n      \"p95\" : 0.0,\n      \"p98\" : 0.0,\n      \"p99\" : 0.0,\n      \"p999\" : 0.0,\n      \"stddev\" : 0.0\n    },\n    \"pipeline.inputRecordsPerBatch.histogramM5\" : {\n      \"count\" : 7,\n      \"max\" : 1000,\n      \"mean\" : 630.903530080653,\n      \"min\" : 0,\n      \"p50\" : 1000.0,\n      \"p75\" : 1000.0,\n      \"p95\" : 1000.0,\n      \"p98\" : 1000.0,\n      \"p99\" : 1000.0,\n      \"p999\" : 1000.0,\n      \"stddev\" : 452.10996611120083\n    },\n    \"pipeline.outputRecordsPerBatch.histogramM5\" : {\n      \"count\" : 7,\n      \"max\" : 1000,\n      \"mean\" : 630.9035300806529,\n      \"min\" : 0,\n      \"p50\" : 1000.0,\n      \"p75\" : 1000.0,\n      \"p95\" : 1000.0,\n      \"p98\" : 1000.0,\n      \"p99\" : 1000.0,\n      \"p999\" : 1000.0,\n      \"stddev\" : 452.10996611120083\n    },\n    \"pipeline.runners.histogramM5\" : {\n      \"count\" : 14,\n      \"max\" : 1,\n      \"mean\" : 0.5021528357205302,\n      \"min\" : 0,\n      \"p50\" : 1.0,\n      \"p75\" : 1.0,\n      \"p95\" : 1.0,\n      \"p98\" : 1.0,\n      \"p99\" : 1.0,\n      \"p999\" : 1.0,\n      \"stddev\" : 0.49999536527687966\n    },\n    \"stage.Directory_01.errorRecords.histogramM5\" : {\n      \"count\" : 7,\n      \"max\" : 0,\n      \"mean\" : 0.0,\n      \"min\" : 0,\n      \"p50\" : 0.0,\n      \"p75\" : 0.0,\n      \"p95\" : 0.0,\n      \"p98\" : 0.0,\n      \"p99\" : 0.0,\n      \"p999\" : 0.0,\n      \"stddev\" : 0.0\n    },\n    \"stage.Directory_01.inputRecords.histogramM5\" : {\n      \"count\" : 7,\n      \"max\" : 0,\n      \"mean\" : 0.0,\n      \"min\" : 0,\n      \"p50\" : 0.0,\n      \"p75\" : 0.0,\n      \"p95\" : 0.0,\n      \"p98\" : 0.0,\n      \"p99\" : 0.0,\n      \"p999\" : 0.0,\n      \"stddev\" : 0.0\n    },\n    \"stage.Directory_01.outputRecords.histogramM5\" : {\n      \"count\" : 7,\n      \"max\" : 1000,\n      \"mean\" : 627.7113694266338,\n      \"min\" : 0,\n      \"p50\" : 1000.0,\n      \"p75\" : 1000.0,\n      \"p95\" : 1000.0,\n      \"p98\" : 1000.0,\n      \"p99\" : 1000.0,\n      \"p999\" : 1000.0,\n      \"stddev\" : 452.75027979111775\n    },\n    \"stage.Directory_01.stageErrors.histogramM5\" : {\n      \"count\" : 7,\n      \"max\" : 0,\n      \"mean\" : 0.0,\n      \"min\" : 0,\n      \"p50\" : 0.0,\n      \"p75\" : 0.0,\n      \"p95\" : 0.0,\n      \"p98\" : 0.0,\n      \"p99\" : 0.0,\n      \"p999\" : 0.0,\n      \"stddev\" : 0.0\n    },\n    \"stage.Elasticsearch_01.errorRecords.histogramM5\" : {\n      \"count\" : 7,\n      \"max\" : 0,\n      \"mean\" : 0.0,\n      \"min\" : 0,\n      \"p50\" : 0.0,\n      \"p75\" : 0.0,\n      \"p95\" : 0.0,\n      \"p98\" : 0.0,\n      \"p99\" : 0.0,\n      \"p999\" : 0.0,\n      \"stddev\" : 0.0\n    },\n    \"stage.Elasticsearch_01.inputRecords.histogramM5\" : {\n      \"count\" : 7,\n      \"max\" : 1000,\n      \"mean\" : 630.9035300806529,\n      \"min\" : 0,\n      \"p50\" : 1000.0,\n      \"p75\" : 1000.0,\n      \"p95\" : 1000.0,\n      \"p98\" : 1000.0,\n      \"p99\" : 1000.0,\n      \"p999\" : 1000.0,\n      \"stddev\" : 452.10996611120083\n    },\n    \"stage.Elasticsearch_01.outputRecords.histogramM5\" : {\n      \"count\" : 7,\n      \"max\" : 1000,\n      \"mean\" : 630.9035300806529,\n      \"min\" : 0,\n      \"p50\" : 1000.0,\n      \"p75\" : 1000.0,\n      \"p95\" : 1000.0,\n      \"p98\" : 1000.0,\n      \"p99\" : 1000.0,\n      \"p999\" : 1000.0,\n      \"stddev\" : 452.10996611120083\n    },\n    \"stage.Elasticsearch_01.stageErrors.histogramM5\" : {\n      \"count\" : 7,\n      \"max\" : 0,\n      \"mean\" : 0.0,\n      \"min\" : 0,\n      \"p50\" : 0.0,\n      \"p75\" : 0.0,\n      \"p95\" : 0.0,\n      \"p98\" : 0.0,\n      \"p99\" : 0.0,\n      \"p999\" : 0.0,\n      \"stddev\" : 0.0\n    },\n    \"stage.FieldMasker_01.errorRecords.histogramM5\" : {\n      \"count\" : 7,\n      \"max\" : 0,\n      \"mean\" : 0.0,\n      \"min\" : 0,\n      \"p50\" : 0.0,\n      \"p75\" : 0.0,\n      \"p95\" : 0.0,\n      \"p98\" : 0.0,\n      \"p99\" : 0.0,\n      \"p999\" : 0.0,\n      \"stddev\" : 0.0\n    },\n    \"stage.FieldMasker_01.inputRecords.histogramM5\" : {\n      \"count\" : 7,\n      \"max\" : 1000,\n      \"mean\" : 627.7113694266337,\n      \"min\" : 0,\n      \"p50\" : 1000.0,\n      \"p75\" : 1000.0,\n      \"p95\" : 1000.0,\n      \"p98\" : 1000.0,\n      \"p99\" : 1000.0,\n      \"p999\" : 1000.0,\n      \"stddev\" : 452.7502797911177\n    },\n    \"stage.FieldMasker_01.outputRecords.histogramM5\" : {\n      \"count\" : 7,\n      \"max\" : 1000,\n      \"mean\" : 627.7113694266338,\n      \"min\" : 0,\n      \"p50\" : 1000.0,\n      \"p75\" : 1000.0,\n      \"p95\" : 1000.0,\n      \"p98\" : 1000.0,\n      \"p99\" : 1000.0,\n      \"p999\" : 1000.0,\n      \"stddev\" : 452.75027979111775\n    },\n    \"stage.FieldMasker_01.stageErrors.histogramM5\" : {\n      \"count\" : 7,\n      \"max\" : 0,\n      \"mean\" : 0.0,\n      \"min\" : 0,\n      \"p50\" : 0.0,\n      \"p75\" : 0.0,\n      \"p95\" : 0.0,\n      \"p98\" : 0.0,\n      \"p99\" : 0.0,\n      \"p999\" : 0.0,\n      \"stddev\" : 0.0\n    }\n  },\n  \"meters\" : {\n    \"custom.Directory_01.spoolQueue.meter\" : {\n      \"count\" : 2,\n      \"m1_rate\" : 0.147151776468577,\n      \"m5_rate\" : 0.3274923012311928,\n      \"m15_rate\" : 0.37420279401264706,\n      \"m30_rate\" : 0.3868864401928023,\n      \"h1_rate\" : 0.39338858152864703,\n      \"h6_rate\" : 0.3988904306708592,\n      \"h12_rate\" : 0.3994448300683632,\n      \"h24_rate\" : 0.39972231865051705,\n      \"mean_rate\" : 0.029910347672045833,\n      \"units\" : \"events/second\"\n    },\n    \"pipeline.batchCount.meter\" : {\n      \"count\" : 7,\n      \"m1_rate\" : 0.172727947007301,\n      \"m5_rate\" : 0.3385001888580894,\n      \"m15_rate\" : 0.3783721737216047,\n      \"m30_rate\" : 0.3890387973058895,\n      \"h1_rate\" : 0.3944820867913214,\n      \"h6_rate\" : 0.3990751235422052,\n      \"h12_rate\" : 0.3995372995005345,\n      \"h24_rate\" : 0.39976858414645605,\n      \"mean_rate\" : 0.1046458188595275,\n      \"units\" : \"events/second\"\n    },\n    \"pipeline.batchErrorMessages.meter\" : {\n      \"count\" : 0,\n      \"m1_rate\" : 0.0,\n      \"m5_rate\" : 0.0,\n      \"m15_rate\" : 0.0,\n      \"m30_rate\" : 0.0,\n      \"h1_rate\" : 0.0,\n      \"h6_rate\" : 0.0,\n      \"h12_rate\" : 0.0,\n      \"h24_rate\" : 0.0,\n      \"mean_rate\" : 0.0,\n      \"units\" : \"events/second\"\n    },\n    \"pipeline.batchErrorRecords.meter\" : {\n      \"count\" : 0,\n      \"m1_rate\" : 0.0,\n      \"m5_rate\" : 0.0,\n      \"m15_rate\" : 0.0,\n      \"m30_rate\" : 0.0,\n      \"h1_rate\" : 0.0,\n      \"h6_rate\" : 0.0,\n      \"h12_rate\" : 0.0,\n      \"h24_rate\" : 0.0,\n      \"mean_rate\" : 0.0,\n      \"units\" : \"events/second\"\n    },\n    \"pipeline.batchInputRecords.meter\" : {\n      \"count\" : 5386,\n      \"m1_rate\" : 168.80200482960691,\n      \"m5_rate\" : 336.8104781073607,\n      \"m15_rate\" : 377.7321739362797,\n      \"m30_rate\" : 388.70841048903054,\n      \"h1_rate\" : 394.3142337335009,\n      \"h6_rate\" : 399.04677318645355,\n      \"h12_rate\" : 399.52310544269625,\n      \"h24_rate\" : 399.76148239282935,\n      \"mean_rate\" : 80.51809243934267,\n      \"units\" : \"events/second\"\n    },\n    \"pipeline.batchOutputRecords.meter\" : {\n      \"count\" : 5386,\n      \"m1_rate\" : 168.80200482960691,\n      \"m5_rate\" : 336.8104781073607,\n      \"m15_rate\" : 377.7321739362797,\n      \"m30_rate\" : 388.70841048903054,\n      \"h1_rate\" : 394.3142337335009,\n      \"h6_rate\" : 399.04677318645355,\n      \"h12_rate\" : 399.52310544269625,\n      \"h24_rate\" : 399.76148239282935,\n      \"mean_rate\" : 80.51814391949519,\n      \"units\" : \"events/second\"\n    },\n    \"stage.Directory_01.errorRecords.meter\" : {\n      \"count\" : 0,\n      \"m1_rate\" : 0.0,\n      \"m5_rate\" : 0.0,\n      \"m15_rate\" : 0.0,\n      \"m30_rate\" : 0.0,\n      \"h1_rate\" : 0.0,\n      \"h6_rate\" : 0.0,\n      \"h12_rate\" : 0.0,\n      \"h24_rate\" : 0.0,\n      \"mean_rate\" : 0.0,\n      \"units\" : \"events/second\"\n    },\n    \"stage.Directory_01.inputRecords.meter\" : {\n      \"count\" : 0,\n      \"m1_rate\" : 0.0,\n      \"m5_rate\" : 0.0,\n      \"m15_rate\" : 0.0,\n      \"m30_rate\" : 0.0,\n      \"h1_rate\" : 0.0,\n      \"h6_rate\" : 0.0,\n      \"h12_rate\" : 0.0,\n      \"h24_rate\" : 0.0,\n      \"mean_rate\" : 0.0,\n      \"units\" : \"events/second\"\n    },\n    \"stage.Directory_01.outputRecords.meter\" : {\n      \"count\" : 5386,\n      \"m1_rate\" : 235.9838504292144,\n      \"m5_rate\" : 497.804656816233,\n      \"m15_rate\" : 563.7912260153637,\n      \"m30_rate\" : 581.6135413071595,\n      \"h1_rate\" : 590.7351481821557,\n      \"h6_rate\" : 598.4458153040467,\n      \"h12_rate\" : 599.2224031188347,\n      \"h24_rate\" : 599.6110753441033,\n      \"mean_rate\" : 80.55051337333614,\n      \"units\" : \"events/second\"\n    },\n    \"stage.Directory_01.stageErrors.meter\" : {\n      \"count\" : 0,\n      \"m1_rate\" : 0.0,\n      \"m5_rate\" : 0.0,\n      \"m15_rate\" : 0.0,\n      \"m30_rate\" : 0.0,\n      \"h1_rate\" : 0.0,\n      \"h6_rate\" : 0.0,\n      \"h12_rate\" : 0.0,\n      \"h24_rate\" : 0.0,\n      \"mean_rate\" : 0.0,\n      \"units\" : \"events/second\"\n    },\n    \"stage.Directory_01:Directory_01OutputLane15260465352240.outputRecords.meter\" : {\n      \"count\" : 5386,\n      \"m1_rate\" : 235.9838504292144,\n      \"m5_rate\" : 497.804656816233,\n      \"m15_rate\" : 563.7912260153637,\n      \"m30_rate\" : 581.6135413071595,\n      \"h1_rate\" : 590.7351481821557,\n      \"h6_rate\" : 598.4458153040467,\n      \"h12_rate\" : 599.2224031188347,\n      \"h24_rate\" : 599.6110753441033,\n      \"mean_rate\" : 80.55302490726544,\n      \"units\" : \"events/second\"\n    },\n    \"stage.Elasticsearch_01.errorRecords.meter\" : {\n      \"count\" : 0,\n      \"m1_rate\" : 0.0,\n      \"m5_rate\" : 0.0,\n      \"m15_rate\" : 0.0,\n      \"m30_rate\" : 0.0,\n      \"h1_rate\" : 0.0,\n      \"h6_rate\" : 0.0,\n      \"h12_rate\" : 0.0,\n      \"h24_rate\" : 0.0,\n      \"mean_rate\" : 0.0,\n      \"units\" : \"events/second\"\n    },\n    \"stage.Elasticsearch_01.inputRecords.meter\" : {\n      \"count\" : 5386,\n      \"m1_rate\" : 235.9838504292144,\n      \"m5_rate\" : 497.804656816233,\n      \"m15_rate\" : 563.7912260153637,\n      \"m30_rate\" : 581.6135413071595,\n      \"h1_rate\" : 590.7351481821557,\n      \"h6_rate\" : 598.4458153040467,\n      \"h12_rate\" : 599.2224031188347,\n      \"h24_rate\" : 599.6110753441033,\n      \"mean_rate\" : 80.5642080323322,\n      \"units\" : \"events/second\"\n    },\n    \"stage.Elasticsearch_01.outputRecords.meter\" : {\n      \"count\" : 5386,\n      \"m1_rate\" : 235.9838504292144,\n      \"m5_rate\" : 497.804656816233,\n      \"m15_rate\" : 563.7912260153637,\n      \"m30_rate\" : 581.6135413071595,\n      \"h1_rate\" : 590.7351481821557,\n      \"h6_rate\" : 598.4458153040467,\n      \"h12_rate\" : 599.2224031188347,\n      \"h24_rate\" : 599.6110753441033,\n      \"mean_rate\" : 80.56438791949255,\n      \"units\" : \"events/second\"\n    },\n    \"stage.Elasticsearch_01.stageErrors.meter\" : {\n      \"count\" : 0,\n      \"m1_rate\" : 0.0,\n      \"m5_rate\" : 0.0,\n      \"m15_rate\" : 0.0,\n      \"m30_rate\" : 0.0,\n      \"h1_rate\" : 0.0,\n      \"h6_rate\" : 0.0,\n      \"h12_rate\" : 0.0,\n      \"h24_rate\" : 0.0,\n      \"mean_rate\" : 0.0,\n      \"units\" : \"events/second\"\n    },\n    \"stage.FieldMasker_01.errorRecords.meter\" : {\n      \"count\" : 0,\n      \"m1_rate\" : 0.0,\n      \"m5_rate\" : 0.0,\n      \"m15_rate\" : 0.0,\n      \"m30_rate\" : 0.0,\n      \"h1_rate\" : 0.0,\n      \"h6_rate\" : 0.0,\n      \"h12_rate\" : 0.0,\n      \"h24_rate\" : 0.0,\n      \"mean_rate\" : 0.0,\n      \"units\" : \"events/second\"\n    },\n    \"stage.FieldMasker_01.inputRecords.meter\" : {\n      \"count\" : 5386,\n      \"m1_rate\" : 235.9838504292144,\n      \"m5_rate\" : 497.804656816233,\n      \"m15_rate\" : 563.7912260153637,\n      \"m30_rate\" : 581.6135413071595,\n      \"h1_rate\" : 590.7351481821557,\n      \"h6_rate\" : 598.4458153040467,\n      \"h12_rate\" : 599.2224031188347,\n      \"h24_rate\" : 599.6110753441033,\n      \"mean_rate\" : 80.55483765161182,\n      \"units\" : \"events/second\"\n    },\n    \"stage.FieldMasker_01.outputRecords.meter\" : {\n      \"count\" : 5386,\n      \"m1_rate\" : 235.9838504292144,\n      \"m5_rate\" : 497.804656816233,\n      \"m15_rate\" : 563.7912260153637,\n      \"m30_rate\" : 581.6135413071595,\n      \"h1_rate\" : 590.7351481821557,\n      \"h6_rate\" : 598.4458153040467,\n      \"h12_rate\" : 599.2224031188347,\n      \"h24_rate\" : 599.6110753441033,\n      \"mean_rate\" : 80.55497600929166,\n      \"units\" : \"events/second\"\n    },\n    \"stage.FieldMasker_01.stageErrors.meter\" : {\n      \"count\" : 0,\n      \"m1_rate\" : 0.0,\n      \"m5_rate\" : 0.0,\n      \"m15_rate\" : 0.0,\n      \"m30_rate\" : 0.0,\n      \"h1_rate\" : 0.0,\n      \"h6_rate\" : 0.0,\n      \"h12_rate\" : 0.0,\n      \"h24_rate\" : 0.0,\n      \"mean_rate\" : 0.0,\n      \"units\" : \"events/second\"\n    },\n    \"stage.FieldMasker_01:FieldMasker_01OutputLane15260466335330.outputRecords.meter\" : {\n      \"count\" : 5386,\n      \"m1_rate\" : 235.9838504292144,\n      \"m5_rate\" : 497.804656816233,\n      \"m15_rate\" : 563.7912260153637,\n      \"m30_rate\" : 581.6135413071595,\n      \"h1_rate\" : 590.7351481821557,\n      \"h6_rate\" : 598.4458153040467,\n      \"h12_rate\" : 599.2224031188347,\n      \"h24_rate\" : 599.6110753441033,\n      \"mean_rate\" : 80.55698133456364,\n      \"units\" : \"events/second\"\n    }\n  },\n  \"timers\" : {\n    \"pipeline.batchProcessing.timer\" : {\n      \"count\" : 7,\n      \"max\" : 60.06400000000001,\n      \"mean\" : 60.06400000000001,\n      \"min\" : 60.06400000000001,\n      \"p50\" : 60.06400000000001,\n      \"p75\" : 60.06400000000001,\n      \"p95\" : 60.06400000000001,\n      \"p98\" : 60.06400000000001,\n      \"p99\" : 60.06400000000001,\n      \"p999\" : 60.06400000000001,\n      \"stddev\" : 0.0,\n      \"m15_rate\" : 0.3783721737216047,\n      \"m1_rate\" : 0.172727947007301,\n      \"m5_rate\" : 0.3385001888580894,\n      \"mean_rate\" : 0.10464439441038828,\n      \"duration_units\" : \"seconds\",\n      \"rate_units\" : \"calls/second\"\n    },\n    \"stage.Directory_01.batchProcessing.timer\" : {\n      \"count\" : 7,\n      \"max\" : 60.063,\n      \"mean\" : 60.063,\n      \"min\" : 60.063,\n      \"p50\" : 60.063,\n      \"p75\" : 60.063,\n      \"p95\" : 60.063,\n      \"p98\" : 60.063,\n      \"p99\" : 60.063,\n      \"p999\" : 60.063,\n      \"stddev\" : 0.0,\n      \"m15_rate\" : 0.5644312258006888,\n      \"m1_rate\" : 0.23990979260690856,\n      \"m5_rate\" : 0.4994943675669616,\n      \"mean_rate\" : 0.10468750853240583,\n      \"duration_units\" : \"seconds\",\n      \"rate_units\" : \"calls/second\"\n    },\n    \"stage.Elasticsearch_01.batchProcessing.timer\" : {\n      \"count\" : 7,\n      \"max\" : 0.0,\n      \"mean\" : 0.0,\n      \"min\" : 0.0,\n      \"p50\" : 0.0,\n      \"p75\" : 0.0,\n      \"p95\" : 0.0,\n      \"p98\" : 0.0,\n      \"p99\" : 0.0,\n      \"p999\" : 0.0,\n      \"stddev\" : 0.0,\n      \"m15_rate\" : 0.5644312258006888,\n      \"m1_rate\" : 0.23990979260690856,\n      \"m5_rate\" : 0.4994943675669616,\n      \"mean_rate\" : 0.10470527879621999,\n      \"duration_units\" : \"seconds\",\n      \"rate_units\" : \"calls/second\"\n    },\n    \"stage.FieldMasker_01.batchProcessing.timer\" : {\n      \"count\" : 7,\n      \"max\" : 0.0,\n      \"mean\" : 0.0,\n      \"min\" : 0.0,\n      \"p50\" : 0.0,\n      \"p75\" : 0.0,\n      \"p95\" : 0.0,\n      \"p98\" : 0.0,\n      \"p99\" : 0.0,\n      \"p999\" : 0.0,\n      \"stddev\" : 0.0,\n      \"m15_rate\" : 0.5644312258006888,\n      \"m1_rate\" : 0.23990979260690856,\n      \"m5_rate\" : 0.4994943675669616,\n      \"mean_rate\" : 0.10469360612852448,\n      \"duration_units\" : \"seconds\",\n      \"rate_units\" : \"calls/second\"\n    }\n  }\n}",
  "retryAttempt" : 0,
  "nextRetryTimeStamp" : 0,
  "name" : "IngestingLocalDataintoAzureDataLakeStorec8d1d823-9fb7-4c13-bd55-1d77f1526f06"
}